indjections/__init__.py
indjections/core.py
indjections/utils.py
indjections/management/__init__.py
indjections/management/commands/__init__.py
indjections/management/commands/indject.py
indjections/packages/__init__.py
indjections/packages/_create-react-app.py
indjections/packages/_make_factories.py
indjections/packages/_make_protected_admin.py
indjections/packages/_make_users_app.py
indjections/packages/django-allauth.py
indjections/packages/django-cors-headers.py
indjections/packages/django-debug-toolbar.py
indjections/packages/django-hijack.py
indjections/packages/django-material-admin.py
indjections/packages/django.py
indjections/packages/djangorestframework.py
tests/main/__init__.py
tests/main/apps.py
tests/main/models.py
tests/main/serializers.py
tests/main/views.py
tests/main/migrations/0001_initial.py
tests/main/migrations/__init__.py
indjections-0.0.4.dist-info/LICENSE
indjections-0.0.4.dist-info/METADATA
indjections-0.0.4.dist-info/WHEEL
indjections-0.0.4.dist-info/top_level.txt
indjections-0.0.4.dist-info/RECORD
