Metadata-Version: 2.1
Name: indjections
Version: 0.0.4
Summary: Enables one-line installation of Django packages by injecting code in the right places.
Home-page: UNKNOWN
License: UNKNOWN
Platform: UNKNOWN
Classifier: Programming Language :: Python :: 3.6
Classifier: Programming Language :: Python :: 3.7
Classifier: Programming Language :: Python :: 3.8
Requires-Python: >=2.7, !=3.0.*, !=3.1.*, !=3.2.*, !=3.3.*, !=3.4.*, !=3.5.*, <4
Requires-Dist: toml
Requires-Dist: colorama
Provides-Extra: dev
Requires-Dist: pytest ; extra == 'dev'
Requires-Dist: ipython ; extra == 'dev'
Requires-Dist: pytest-cov ; extra == 'dev'
Requires-Dist: pytest-django ; extra == 'dev'
Requires-Dist: django ; extra == 'dev'
Requires-Dist: djangorestframework ; extra == 'dev'
Requires-Dist: indjections ; extra == 'dev'
Requires-Dist: pytest-pythonpath ; extra == 'dev'
